pi_touch/__init__.py
pi_touch/button.py
pi_touch/cli.py
pi_touch/events.py
pi_touch/gpio.py
pi_touch/manager.py
pi_touch/utils.py
pi_touch-0.1.0.dist-info/METADATA
pi_touch-0.1.0.dist-info/WHEEL
pi_touch-0.1.0.dist-info/entry_points.txt
pi_touch-0.1.0.dist-info/top_level.txt
pi_touch-0.1.0.dist-info/RECORD
