Metadata-Version: 2.1
Name: pi-touch
Version: 0.1.0
Summary: Control PI Touch Screen with GPIO
Home-page: 
Author: Eric Stasney
Author-email: estasney@users.noreply.github.com
License: MIT
Classifier: License :: OSI Approved :: MIT License
Classifier: Programming Language :: Python
Requires-Python: >=3.9.0
Requires-Dist: click
Requires-Dist: RPi.GPIO
